odoo/addons/account_asset_low_value/README.rst
odoo/addons/account_asset_low_value/__init__.py
odoo/addons/account_asset_low_value/__manifest__.py
odoo/addons/account_asset_low_value/i18n/account_asset_low_value.pot
odoo/addons/account_asset_low_value/i18n/es.po
odoo/addons/account_asset_low_value/i18n/it.po
odoo/addons/account_asset_low_value/models/__init__.py
odoo/addons/account_asset_low_value/models/account_asset.py
odoo/addons/account_asset_low_value/readme/CONTRIBUTORS.rst
odoo/addons/account_asset_low_value/readme/DESCRIPTION.rst
odoo/addons/account_asset_low_value/static/description/icon.png
odoo/addons/account_asset_low_value/static/description/index.html
odoo/addons/account_asset_low_value/tests/__init__.py
odoo/addons/account_asset_low_value/tests/test_asset_low_value.py
odoo/addons/account_asset_low_value/views/account_asset_views.xml
odoo/addons/account_asset_low_value/wizard/__init__.py
odoo/addons/account_asset_low_value/wizard/account_asset_remove.py
odoo/addons/account_asset_low_value/wizard/account_asset_remove.xml
odoo14_addon_account_asset_low_value-14.0.1.0.1.dev7.dist-info/METADATA
odoo14_addon_account_asset_low_value-14.0.1.0.1.dev7.dist-info/WHEEL
odoo14_addon_account_asset_low_value-14.0.1.0.1.dev7.dist-info/top_level.txt
odoo14_addon_account_asset_low_value-14.0.1.0.1.dev7.dist-info/RECORD
